catnet/__init__.py
catnet/datasets.py
catnet/layers.py
catnet/loss.py
catnet/losses.py
catnet/nn.py
catnet/optim.py
catnet/optimize.py
catnet/tensor.py
catnet_RedCatTeam-1.0.2.dist-info/LICENSE
catnet_RedCatTeam-1.0.2.dist-info/METADATA
catnet_RedCatTeam-1.0.2.dist-info/WHEEL
catnet_RedCatTeam-1.0.2.dist-info/top_level.txt
catnet_RedCatTeam-1.0.2.dist-info/RECORD
