Metadata-Version: 2.1
Name: catnet_RedCatTeam
Version: 1.0.2
Summary: A package for simple machine learning (AI)
Author-email: RedCatTeam <evgeniy.coder@gmail.com>
Project-URL: Homepage, https://cat-ai-project.ru/catnet/
Project-URL: Issues, https://cat-ai-project.ru/catnet/issues
Classifier: Programming Language :: Python :: 3
Classifier: License :: OSI Approved :: MIT License
Classifier: Operating System :: OS Independent
Requires-Python: >=3.10
License-File: LICENSE
